iagitbetter/__init__.py
iagitbetter/__main__.py
iagitbetter/iagitbetter.py
iagitbetter-1.1.1.dist-info/licenses/LICENSE
tests/__init__.py
tests/constants.py
tests/test_iagitbetter.py
tests/test_utils.py
iagitbetter-1.1.1.dist-info/METADATA
iagitbetter-1.1.1.dist-info/WHEEL
iagitbetter-1.1.1.dist-info/entry_points.txt
iagitbetter-1.1.1.dist-info/top_level.txt
iagitbetter-1.1.1.dist-info/RECORD
