Metadata-Version: 2.4
Name: iagitbetter
Version: 1.1.1
Summary: Archiving any git repository to the Internet Archive
Home-page: https://github.com/Andres9890/iagitbetter
Author: Andres99
License: GNU GENERAL PUBLIC LICENSE
Project-URL: Homepage, https://github.com/Andres9890/iagitbetter
Project-URL: Documentation, https://github.com/Andres9890/iagitbetter/blob/main/README.md
Project-URL: Bug Tracker, https://github.com/Andres9890/iagitbetter/issues
Project-URL: Source Code, https://github.com/Andres9890/iagitbetter
Keywords: git,archive,internet-archive,internetarchive,github,gitlab,bitbucket,repository,self-hosted,gitea,forgejo
Platform: any
Classifier: Development Status :: 5 - Production/Stable
Classifier: Intended Audience :: Developers
Classifier: License :: OSI Approved :: GNU General Public License v3 (GPLv3)
Classifier: Programming Language :: Python :: 3
Classifier: Programming Language :: Python :: 3.9
Classifier: Programming Language :: Python :: 3.10
Classifier: Programming Language :: Python :: 3.11
Classifier: Programming Language :: Python :: 3.12
Classifier: Topic :: Software Development :: Version Control :: Git
Classifier: Topic :: System :: Archiving
Requires-Python: >=3.9
License-File: LICENSE
Requires-Dist: requests>=2.32.5
Requires-Dist: internetarchive>=5.5.1
Requires-Dist: GitPython>=3.1.45
Requires-Dist: markdown2>=2.5.4
Requires-Dist: docutils>=0.22.2
Provides-Extra: dev
Requires-Dist: pytest>=6.0; extra == "dev"
Requires-Dist: black; extra == "dev"
Requires-Dist: flake8; extra == "dev"
Dynamic: home-page
Dynamic: license-file
Dynamic: platform
Dynamic: requires-python
